jetstreamcli/__init__.py
jetstreamcli/cmds.py
jetstreamcli/config.py
jetstreamcli/files.py
jetstreamcli/frames.py
jetstreamcli/jetstream.py
jetstreamcli/projectscmds.py
jetstreamcli/robloxcmds.py
jetstreamcli/robloxfuncs.py
jetstreamcli-0.1.22.dist-info/LICENSE
jetstreamcli-0.1.22.dist-info/METADATA
jetstreamcli-0.1.22.dist-info/WHEEL
jetstreamcli-0.1.22.dist-info/entry_points.txt
jetstreamcli-0.1.22.dist-info/RECORD
